Metadata-Version: 1.1
Name: sparkfun-qwiic-twist
Version: 0.9.0
Summary: SparkFun Electronics qwiic Twist
Home-page: https://www.sparkfun.com/products/15083
Author: SparkFun Electronics
Author-email: info@sparkfun.com
License: MIT
Keywords: electronics,maker
Platform: UNKNOWN
Classifier: Development Status :: 4 - Beta
Classifier: Intended Audience :: Developers
Classifier: Topic :: Software Development :: Build Tools
Classifier: License :: OSI Approved :: MIT License
Classifier: Programming Language :: Python :: 2.7
Classifier: Programming Language :: Python :: 3.5
Classifier: Programming Language :: Python :: 3.6
Classifier: Programming Language :: Python :: 3.7
